AUTHORS
COPYING
README
build.sh
ez_setup.py
setup.cfg
setup.py
ethumb/__init__.py
ethumb/ethumb.c_ethumb.pyx
ethumb/ethumb.client.pyx
examples/01-simple.py
include/ethumb/__init__.py
include/ethumb/c_ethumb.pxd
include/ethumb/client.pxd
python_ethumb.egg-info/PKG-INFO
python_ethumb.egg-info/SOURCES.txt
python_ethumb.egg-info/dependency_links.txt
python_ethumb.egg-info/not-zip-safe
python_ethumb.egg-info/top_level.txt