Metadata-Version: 1.0
Name: python-ethumb
Version: 0.2
Summary: Python bindings for Ethumb
Home-page: http://www.enlightenment.org/
Author: Rafael Antognolli
Author-email: antognolli@profusion.mobi
License: LGPL
Keywords: wrapper binding enlightenment graphics jpg jpeg png thumbnail freedesktop.org
Platform: UNKNOWN
Classifier: Development Status :: 3 - Alpha
Classifier: Environment :: Console :: Framebuffer
Classifier: Environment :: X11 Applications
Classifier: Intended Audience :: Developers
Classifier: License :: OSI Approved :: GNU Library or Lesser General Public License (LGPL)
Classifier: Operating System :: MacOS :: MacOS X
Classifier: Operating System :: POSIX
Classifier: Programming Language :: C
Classifier: Programming Language :: Python
Classifier: Topic :: Software Development :: Libraries :: Python Modules
Classifier: Topic :: Software Development :: User Interfaces
